Metadata-Version: 2.1
Name: crawler_update_detect
Version: 1.0.1
Summary: A package to detect whether html ODM and text has been change
Author: Frank
Requires-Python: >=3.8
License-File: LICENSE
